cloudstorage/__init__.py
cloudstorage/base.py
cloudstorage/exceptions.py
cloudstorage/helpers.py
cloudstorage/messages.py
cloudstorage/structures.py
cloudstorage/typed.py
cloudstorage/utils.py
cloudstorage/drivers/__init__.py
cloudstorage/drivers/amazon.py
cloudstorage/drivers/google.py
cloudstorage/drivers/local.py
cloudstorage/drivers/microsoft.py
cloudstorage/drivers/minio.py
cloudstorage/drivers/rackspace.py
cloudstorage-0.10.1.dist-info/AUTHORS.rst
cloudstorage-0.10.1.dist-info/LICENSE
cloudstorage-0.10.1.dist-info/METADATA
cloudstorage-0.10.1.dist-info/WHEEL
cloudstorage-0.10.1.dist-info/top_level.txt
cloudstorage-0.10.1.dist-info/RECORD
