Metadata-Version: 2.1
Name: cloudstorage
Version: 0.10.1
Summary: Unified cloud storage API for storage services.
Home-page: https://github.com/scottwernervt/cloudstorage/
Author: Scott Werner
Author-email: scott.werner.vt@gmail.com
License: MIT
Keywords: storage amazon aws s3 azure rackspace cloudfiles google cloudstorage gcs minio
Platform: UNKNOWN
Classifier: Development Status :: 3 - Alpha
Classifier: Environment :: Web Environment
Classifier: Intended Audience :: Developers
Classifier: Intended Audience :: Information Technology
Classifier: Intended Audience :: System Administrators
Classifier: License :: OSI Approved :: MIT License
Classifier: Operating System :: OS Independent
Classifier: Programming Language :: Python :: 3 :: Only
Classifier: Programming Language :: Python :: 3.5
Classifier: Programming Language :: Python :: 3.6
Classifier: Programming Language :: Python :: 3.7
Classifier: Topic :: Internet
Classifier: Topic :: Software Development :: Libraries :: Python Modules
Provides-Extra: amazon
Provides-Extra: google
Provides-Extra: local
Provides-Extra: microsoft
Provides-Extra: minio
Provides-Extra: rackspace
Provides-Extra: docs
